typing_tool-0.1.10.dist-info/METADATA
typing_tool-0.1.10.dist-info/WHEEL
typing_tool-0.1.10.dist-info/entry_points.txt
typing_tool-0.1.10.dist-info/licenses/LICENSE
typing_tool/__init__.py
typing_tool/call.py
typing_tool/config.py
typing_tool/overload.py
typing_tool/type_utils.py
typing_tool/typevar/__init__.py
typing_tool/typevar/typevar.py
typing_tool-0.1.10.dist-info/RECORD
