Metadata-Version: 2.1
Name: typing_tool
Version: 0.1.10
Summary: python typing tool
Author-Email: luxuncang <luxuncang@qq.com>
License: MIT
Requires-Python: >=3.10
Requires-Dist: pydantic>=2.7.0
Requires-Dist: typing-inspect>=0.9.0
Requires-Dist: typing-extensions>=4.11.0
